py_dss_interface/DSS.py
py_dss_interface/__init__.py
py_dss_interface/configurations.json
py_dss_interface/models/Base.py
py_dss_interface/models/Bridge.py
py_dss_interface/models/__init__.py
py_dss_interface/models/ActiveClass/ActiveClass.py
py_dss_interface/models/ActiveClass/ActiveClassI.py
py_dss_interface/models/ActiveClass/ActiveClassS.py
py_dss_interface/models/ActiveClass/ActiveClassV.py
py_dss_interface/models/ActiveClass/__init__.py
py_dss_interface/models/Bus/Bus.py
py_dss_interface/models/Bus/BusF.py
py_dss_interface/models/Bus/BusI.py
py_dss_interface/models/Bus/BusS.py
py_dss_interface/models/Bus/BusV.py
py_dss_interface/models/Bus/__init__.py
py_dss_interface/models/CMathLib/CMathLib.py
py_dss_interface/models/CMathLib/CMathLibF.py
py_dss_interface/models/CMathLib/CMathLibV.py
py_dss_interface/models/CMathLib/__init__.py
py_dss_interface/models/CapControls/CapControls.py
py_dss_interface/models/CapControls/CapControlsF.py
py_dss_interface/models/CapControls/CapControlsI.py
py_dss_interface/models/CapControls/CapControlsS.py
py_dss_interface/models/CapControls/CapControlsV.py
py_dss_interface/models/CapControls/__init__.py
py_dss_interface/models/Capacitors/Capacitors.py
py_dss_interface/models/Capacitors/CapacitorsF.py
py_dss_interface/models/Capacitors/CapacitorsI.py
py_dss_interface/models/Capacitors/CapacitorsS.py
py_dss_interface/models/Capacitors/CapacitorsV.py
py_dss_interface/models/Capacitors/__init__.py
py_dss_interface/models/Circuit/Circuit.py
py_dss_interface/models/Circuit/CircuitF.py
py_dss_interface/models/Circuit/CircuitI.py
py_dss_interface/models/Circuit/CircuitS.py
py_dss_interface/models/Circuit/CircuitV.py
py_dss_interface/models/Circuit/__init__.py
py_dss_interface/models/CktElement/CktElement.py
py_dss_interface/models/CktElement/CktElementF.py
py_dss_interface/models/CktElement/CktElementI.py
py_dss_interface/models/CktElement/CktElementS.py
py_dss_interface/models/CktElement/CktElementV.py
py_dss_interface-2.2.1.dist-info/licenses/LICENSE
py_dss_interface-2.2.1.dist-info/METADATA
py_dss_interface-2.2.1.dist-info/WHEEL
py_dss_interface-2.2.1.dist-info/top_level.txt
py_dss_interface-2.2.1.dist-info/RECORD
