Metadata-Version: 2.4
Name: py-dss-interface
Version: 2.2.1
Summary: Python interface for controlling OpenDSS Powered by EPRI.
Author-email: Paulo Radatz <paulo.radatz@gmail.com>
License: MIT
Project-URL: Documentation, https://py_dss_interface.readthedocs.io/
Project-URL: Changelog, https://py_dss_interface.readthedocs.io/en/latest/changelog.html
Project-URL: Issue Tracker, https://github.com/PauloRadatz/py_dss_interface/issues
Project-URL: Source, https://github.com/PauloRadatz/py_dss_interface
Keywords: OpenDSS,Python,Power Systems,Distribution Systems,Energy
Classifier: Development Status :: 4 - Beta
Classifier: Intended Audience :: Science/Research
Classifier: License :: OSI Approved :: MIT License
Classifier: Operating System :: Microsoft :: Windows
Classifier: Operating System :: POSIX :: Linux
Classifier: Programming Language :: Python :: 3
Classifier: Programming Language :: Python :: 3.9
Classifier: Programming Language :: Python :: 3.10
Classifier: Programming Language :: Python :: 3.11
Classifier: Programming Language :: Python :: 3.12
Classifier: Topic :: Scientific/Engineering
Classifier: Topic :: Software Development :: Libraries :: Python Modules
Requires-Python: >=3.9
License-File: LICENSE
Provides-Extra: dev
Requires-Dist: pytest; extra == "dev"
Requires-Dist: pytest-cov; extra == "dev"
Requires-Dist: sphinx-rtd-theme; extra == "dev"
Requires-Dist: nbsphinx; extra == "dev"
Requires-Dist: black; extra == "dev"
Requires-Dist: pre-commit; extra == "dev"
Requires-Dist: tox; extra == "dev"
Requires-Dist: twine; extra == "dev"
Requires-Dist: ipython; extra == "dev"
Requires-Dist: flake8; extra == "dev"
Dynamic: license-file
